// class version 50.0 (50)
// access flags 0x21
public class ama extends ajc  {

  // compiled from: BlockMobSpawner.java

  // access flags 0x1A
  private final static Ljava/lang/String; __OBFID = "CL_00000269"

  // access flags 0x2
  private Ljava/util/Random; rand

  // access flags 0x4
  protected <init>()V
   L0
    LINENUMBER 19 L0
    ALOAD 0
    GETSTATIC awt.e : Lawt;
    INVOKESPECIAL ajc.<init> (Lawt;)V
   L1
    LINENUMBER 42 L1
    ALOAD 0
    NEW java/util/Random
    DUP
    INVOKESPECIAL java/util/Random.<init> ()V
    PUTFIELD ama.rand : Ljava/util/Random;
   L2
    LINENUMBER 20 L2
    RETURN
   L3
    LOCALVARIABLE this Lama; L0 L3 0
    MAXSTACK = 3
    MAXLOCALS = 1

  // access flags 0x1
  public a(Lahb;I)Laor;
   L0
    LINENUMBER 24 L0
    NEW apj
    DUP
    INVOKESPECIAL apj.<init> ()V
    ARETURN
   L1
    LOCALVARIABLE this Lama; L0 L1 0
    LOCALVARIABLE p_149915_1_ Lahb; L0 L1 1
    LOCALVARIABLE p_149915_2_ I L0 L1 2
    MAXSTACK = 2
    MAXLOCALS = 3

  // access flags 0x1
  public a(ILjava/util/Random;I)Ladb;
   L0
    LINENUMBER 29 L0
    ACONST_NULL
    ARETURN
   L1
    LOCALVARIABLE this Lama; L0 L1 0
    LOCALVARIABLE p_149650_1_ I L0 L1 1
    LOCALVARIABLE p_149650_2_ Ljava/util/Random; L0 L1 2
    LOCALVARIABLE p_149650_3_ I L0 L1 3
    MAXSTACK = 1
    MAXLOCALS = 4

  // access flags 0x1
  public a(Ljava/util/Random;)I
   L0
    LINENUMBER 34 L0
    ICONST_0
    IRETURN
   L1
    LOCALVARIABLE this Lama; L0 L1 0
    LOCALVARIABLE p_149745_1_ Ljava/util/Random; L0 L1 1
    MAXSTACK = 1
    MAXLOCALS = 2

  // access flags 0x1
  public a(Lahb;IIIIFI)V
   L0
    LINENUMBER 39 L0
    ALOAD 0
    ALOAD 1
    ILOAD 2
    ILOAD 3
    ILOAD 4
    ILOAD 5
    FLOAD 6
    ILOAD 7
    INVOKESPECIAL ajc.a (Lahb;IIIIFI)V
   L1
    LINENUMBER 40 L1
    RETURN
   L2
    LOCALVARIABLE this Lama; L0 L2 0
    LOCALVARIABLE p_149690_1_ Lahb; L0 L2 1
    LOCALVARIABLE p_149690_2_ I L0 L2 2
    LOCALVARIABLE p_149690_3_ I L0 L2 3
    LOCALVARIABLE p_149690_4_ I L0 L2 4
    LOCALVARIABLE p_149690_5_ I L0 L2 5
    LOCALVARIABLE p_149690_6_ F L0 L2 6
    LOCALVARIABLE p_149690_7_ I L0 L2 7
    MAXSTACK = 8
    MAXLOCALS = 8

  // access flags 0x1
  public getExpDrop(Lahl;II)I
   L0
    LINENUMBER 46 L0
    BIPUSH 15
    ALOAD 0
    GETFIELD ama.rand : Ljava/util/Random;
    BIPUSH 15
    INVOKEVIRTUAL java/util/Random.nextInt (I)I
    IADD
    ALOAD 0
    GETFIELD ama.rand : Ljava/util/Random;
    BIPUSH 15
    INVOKEVIRTUAL java/util/Random.nextInt (I)I
    IADD
    IRETURN
   L1
    LOCALVARIABLE this Lama; L0 L1 0
    LOCALVARIABLE world Lahl; L0 L1 1
    LOCALVARIABLE metadata I L0 L1 2
    LOCALVARIABLE fortune I L0 L1 3
    MAXSTACK = 3
    MAXLOCALS = 4

  // access flags 0x1
  public c()Z
   L0
    LINENUMBER 51 L0
    ICONST_0
    IRETURN
   L1
    LOCALVARIABLE this Lama; L0 L1 0
    MAXSTACK = 1
    MAXLOCALS = 1

  // access flags 0x1
  public d(Lahb;III)Ladb;
  @Lcpw/mods/fml/relauncher/SideOnly;(value=Lcpw/mods/fml/relauncher/Side;.CLIENT)
   L0
    LINENUMBER 57 L0
    ICONST_0
    INVOKESTATIC adb.d (I)Ladb;
    ARETURN
   L1
    LOCALVARIABLE this Lama; L0 L1 0
    LOCALVARIABLE p_149694_1_ Lahb; L0 L1 1
    LOCALVARIABLE p_149694_2_ I L0 L1 2
    LOCALVARIABLE p_149694_3_ I L0 L1 3
    LOCALVARIABLE p_149694_4_ I L0 L1 4
    MAXSTACK = 1
    MAXLOCALS = 5

  // access flags 0x1
  public a(Lahb;IIILsv;Ladd;)V
    ILOAD 2
    PUTSTATIC codechicken/nei/ItemMobSpawner.placedX : I
    ILOAD 3
    PUTSTATIC codechicken/nei/ItemMobSpawner.placedY : I
    ILOAD 4
    PUTSTATIC codechicken/nei/ItemMobSpawner.placedZ : I
    RETURN
    MAXSTACK = 1
    MAXLOCALS = 7
}
